miniserial/__init__.py
miniserial/serialization.py
miniserial-0.2.6.dist-info/METADATA
miniserial-0.2.6.dist-info/WHEEL
miniserial-0.2.6.dist-info/licenses/LICENSE
miniserial-0.2.6.dist-info/RECORD
