Metadata-Version: 2.1
Name: miniserial
Version: 0.2.6
Summary: Simple, fast, and space-efficient (de)serialization for simple Python classes
Project-URL: Homepage, https://github.com/SinclaM/miniserial
Author-email: Matthew Sinclair <sinclam.dev@gmail.com>
License: MIT License
License-File: LICENSE
Keywords: serialization,serialize
Classifier: License :: OSI Approved :: MIT License
Classifier: Programming Language :: Python
Classifier: Programming Language :: Python :: 3
Classifier: Programming Language :: Python :: 3.9
Classifier: Programming Language :: Python :: 3.10
Classifier: Programming Language :: Python :: 3.11
Requires-Python: >=3.9
